sophia_opt/__init__.py
sophia_opt-0.2.2.dist-info/METADATA
sophia_opt-0.2.2.dist-info/WHEEL
sophia_opt-0.2.2.dist-info/licenses/LICENSE
sophia_opt-0.2.2.dist-info/RECORD
