Metadata-Version: 2.3
Name: sophia-opt
Version: 0.2.2
Summary: A community package of the official implementation of “Sophia: A Scalable Stochastic Second-order Optimizer for Language Model Pre-training”
Project-URL: Homepage, https://github.com/fuyutarow/sophia-opt
Project-URL: Repository, https://github.com/fuyutarow/sophia-opt
Author: Liuhong99
Author-email: fuyutarow <fuyutarow@gmail.com>
License-Expression: MIT
License-File: LICENSE
Keywords: optimizer,pytorch,sophia
Requires-Python: >=3.8
Requires-Dist: torch>=2
